nAIme_test/__init__.py
nAIme_test/get_suggestion.py
nAIme_test/GRAFT/GRAFT_Create_Suggestions_for_Family_Trees_Graphs_Using_Ordering_Functions_for_package.py
nAIme_test/GRAFT/__init__.py
nAIme_test/GRAFT/RelevantFiles/RelevantFiles.zip
nAIme_test/GRAFT/RelevantFiles/__init__.py
nAIme_test/Phonetic/__init__.py
nAIme_test/Phonetic/phonetic_suggestion.py
nAIme_test/Phonetic/RelevantFiles/__init__.py
nAIme_test/Phonetic/RelevantFiles/wt_First_Name_phonetic_algorithm_codes.csv
nAIme_test/SpokenName2Vec/__init__.py
nAIme_test/SpokenName2Vec/name2mp3.py
nAIme_test/SpokenName2Vec/run_names_project_sound.py
nAIme_test/SpokenName2Vec/run_sound.py
nAIme_test/SpokenName2Vec/splitDir.py
nAIme_test/SpokenName2Vec/RelevantFiles/RelevantFiles.7z
nAIme_test/SpokenName2Vec/RelevantFiles/__init__.py
test/__init__.py
test/test_myfunctions.py
nAIme_test-0.1.25.dist-info/METADATA
nAIme_test-0.1.25.dist-info/WHEEL
nAIme_test-0.1.25.dist-info/top_level.txt
nAIme_test-0.1.25.dist-info/RECORD
